__init__.py
non_parametric/__init__.py
non_parametric/empirical_cumulative_distribution.py
non_parametric/frequency_table.py
non_parametric/plot_comparision.py
non_parametric/synthetic_data_generator.py
non_parametric_multivariate_data_generator-0.0.3.dist-info/LICENSE
non_parametric_multivariate_data_generator-0.0.3.dist-info/METADATA
non_parametric_multivariate_data_generator-0.0.3.dist-info/WHEEL
non_parametric_multivariate_data_generator-0.0.3.dist-info/top_level.txt
non_parametric_multivariate_data_generator-0.0.3.dist-info/RECORD
