Metadata-Version: 2.1
Name: non-parametric-multivariate-data-generator
Version: 0.0.3
Summary: A small example package
Author-email: "Juan P. Restrepo" <jurest82@eafit.edu.co>, Pablo Osorio <osoriopabl@gmail.com>
License: License text copyright © 2017 MariaDB Corporation Ab, All Rights Reserved.
Project-URL: Homepage, https://github.com/jurest82/SyntheticDataCopulas
Classifier: Programming Language :: Python :: 3.9
Classifier: Operating System :: OS Independent
Requires-Python: >=3.9
License-File: LICENSE
Requires-Dist: pandas (>=1.3.5)
Requires-Dist: matplotlib (>=3.2.2)
Requires-Dist: numpy (>=1.21.6)
Provides-Extra: dev
Requires-Dist: jupyterlab (>=3.2.1) ; extra == 'dev'
Requires-Dist: openpyxl (==3.0.10) ; extra == 'dev'
Requires-Dist: pre-commit (>=3.3) ; extra == 'dev'
Requires-Dist: pytest (>=7.0) ; extra == 'dev'
Requires-Dist: seaborn (==0.11.2) ; extra == 'dev'
Requires-Dist: twine (>=4.0.2) ; extra == 'dev'
